olstecnologia/__init__.py
olstecnologia/app.py
olstecnologia/config/__init__.py
olstecnologia/config/database.py
olstecnologia/config/fbclient.dll
olstecnologia/features/__init__.py
olstecnologia/features/read_fb_for_postgres_feature.py
olstecnologia/features/update_addres_feature.py
olstecnologia/services/__init__.py
olstecnologia/services/check_db_service.py
olstecnologia/services/connection_service.py
olstecnologia/services/services_service.py
olstecnologia/services/utils_service.py
olstecnologia-1.1.6.dist-info/entry_points.txt
olstecnologia-1.1.6.dist-info/METADATA
olstecnologia-1.1.6.dist-info/WHEEL
olstecnologia-1.1.6.dist-info/RECORD
