Metadata-Version: 2.1
Name: olstecnologia
Version: 1.1.6
Summary: 
Author: Julio Pereira
Author-email: juliopereira.dev@gmail.com
Requires-Python: >=3.11,<4.0
Classifier: Programming Language :: Python :: 3
Classifier: Programming Language :: Python :: 3.11
Requires-Dist: fdb (>=2.0.2,<3.0.0)
Requires-Dist: firebird (>=0.0.2,<0.0.3)
Requires-Dist: geopandas (>=0.12.2,<0.13.0)
Requires-Dist: ipdb (>=0.13.13,<0.14.0)
Requires-Dist: psycopg2 (>=2.9.6,<3.0.0)
Requires-Dist: sqlalchemy (==1.4.39)
Requires-Dist: sqlalchemy-firebird (>=0.7.6,<0.8.0)
Requires-Dist: tqdm (>=4.65.0,<5.0.0)
